CHANGELOG.txt
LICENCE.txt
MANIFEST.in
README.txt
_init_.py
setup.py
KinshukBasicCalculator.egg-info/PKG-INFO
KinshukBasicCalculator.egg-info/SOURCES.txt
KinshukBasicCalculator.egg-info/dependency_links.txt
KinshukBasicCalculator.egg-info/top_level.txt