Metadata-Version: 2.4
Name: KinshukBasicCalculator
Version: 0.0.1
Summary: A Basic Calculator
Home-page: 
Author: Kinshuk Gupta
Author-email: kinshukg@iitbhilai.ac.in
License: MIT
Keywords: calculator
Classifier: Development Status :: 5 - Production/Stable
Classifier: Intended Audience :: Education
Classifier: Operating System :: Microsoft :: Windows :: Windows 10
Classifier: License :: OSI Approved :: MIT License
Classifier: Programming Language :: Python :: 3
License-File: LICENCE.txt
Dynamic: author
Dynamic: author-email
Dynamic: classifier
Dynamic: description
Dynamic: keywords
Dynamic: license
Dynamic: license-file
Dynamic: summary
